AUTHORS
COPYING
COPYING.LESSER
README.md
setup.py
pducontrol/__cli.py
pducontrol/__init__.py
pducontrol/__main__.py
pducontrol/__pdu.py
pducontrol/__pdu8100x.py
pducontrol/__pdu_netio_4c.py
pducontrol/__pdu_swh_1023j.py
pducontrol/__snmp.py
pducontrol/__version__.py
pducontrol.egg-info/PKG-INFO
pducontrol.egg-info/SOURCES.txt
pducontrol.egg-info/dependency_links.txt
pducontrol.egg-info/entry_points.txt
pducontrol.egg-info/requires.txt
pducontrol.egg-info/top_level.txt
tests/test_pdu8100x.py
tests/test_snmp.py