Metadata-Version: 2.1
Name: pducontrol
Version: 1.6.2
Summary: A simple package to control PDUs
Home-page: https://bitbucket.org/spectracom/pdu-control/src/master/
Author: Pol Bodet, Nicolas Carrier, Jeremy Connat, Jai Mehra
Author-email: pol.bodet@orolia.com
License: LGPLv3+
Classifier: Development Status :: 3 - Alpha
Classifier: Intended Audience :: Developers
Classifier: Programming Language :: Python :: 3
Classifier: Programming Language :: Python :: 3.6
Classifier: Programming Language :: Python :: 3.7
Classifier: Programming Language :: Python :: 3.8
Classifier: Programming Language :: Python :: 3.9
Classifier: Programming Language :: Python :: 3.10
License-File: COPYING
License-File: COPYING.LESSER
License-File: AUTHORS
Requires-Dist: requests
Requires-Dist: tabulate
Requires-Dist: argcomplete
Requires-Dist: xmltodict
